guam/__init__.py
guam/automl/__init__.py
guam/automl/base.py
guam/config/workflow_config.yaml
guam/datalibs/__init__.py
guam/datalibs/base.py
guam/models/RFmodel.py
guam/models/__init__.py
guam/models/basemodel.py
guam/models/xgbmodel.py
guam/utils/__init__.py
guam/utils/global_variables.py
guam-0.0.3.dist-info/METADATA
guam-0.0.3.dist-info/WHEEL
guam-0.0.3.dist-info/licenses/LICENSE
guam-0.0.3.dist-info/RECORD
