Metadata-Version: 2.4
Name: GUAM
Version: 0.0.3
Summary: GUAM: GPU-based Auto ML for Robust Large Scale Computation.
Project-URL: Homepage, https://github.com/Ign0reLee/GUAM
Project-URL: Bug Tracker, https://github.com/Ign0reLee/GUAM/issues
Author-email: Jeyoung Lee <dlwpdud@gmail.com>, Jia Son <dlwpdud@gmail.com>, Sung Heo <dlwpdud@gmail.com>
License: 
License-File: LICENSE
Classifier: License :: OSI Approved :: Apache Software License
Classifier: Operating System :: OS Independent
Classifier: Programming Language :: Python :: 3
Requires-Python: >=3.10
Requires-Dist: cupy-cuda11x==13.6.*
Requires-Dist: numpy
Requires-Dist: omegaconf
Requires-Dist: pandas
